<annotation>
    <folder>images</folder>
    <filename>sperm_morph_461_resized.jpeg</filename>
    <path>/Users/Manav/Desktop/cs231n-project/faster-rcnn-data/images/sperm_morph_461_resized.jpeg</path>
    <source>
        <database>Unknown</database>
    </source>
    <size>
        <width>776</width>
        <height>582</height>
        <depth>3</depth>
    </size>
    <segmented>0</segmented>
    <object>
        <name>Abnormal</name>
        <pose>Unspecified</pose>
        <truncated>0</truncated>
        <difficult>0</difficult>
        <bndbox>
            <xmin>166</xmin>
            <ymin>72</ymin>
            <xmax>700</xmax>
            <ymax>338</ymax>
        </bndbox>
    </object>    <object>
        <name>Abnormal</name>
        <pose>Unspecified</pose>
        <truncated>0</truncated>
        <difficult>0</difficult>
        <bndbox>
            <xmin>8</xmin>
            <ymin>267</ymin>
            <xmax>458</xmax>
            <ymax>495</ymax>
        </bndbox>
    </object>
</annotation>
