<annotation>
    <folder>images</folder>
    <filename>sperm_morph_527_resized.jpeg</filename>
    <path>/Users/Manav/Desktop/cs231n-project/faster-rcnn-data/images/sperm_morph_527_resized.jpeg</path>
    <source>
        <database>Unknown</database>
    </source>
    <size>
        <width>776</width>
        <height>582</height>
        <depth>3</depth>
    </size>
    <segmented>0</segmented>
    <object>
        <name>Abnormal</name>
        <pose>Unspecified</pose>
        <truncated>0</truncated>
        <difficult>0</difficult>
        <bndbox>
            <xmin>5</xmin>
            <ymin>214</ymin>
            <xmax>76</xmax>
            <ymax>317</ymax>
        </bndbox>
    </object>    <object>
        <name>Abnormal</name>
        <pose>Unspecified</pose>
        <truncated>0</truncated>
        <difficult>0</difficult>
        <bndbox>
            <xmin>104</xmin>
            <ymin>252</ymin>
            <xmax>194</xmax>
            <ymax>369</ymax>
        </bndbox>
    </object>    <object>
        <name>Abnormal</name>
        <pose>Unspecified</pose>
        <truncated>0</truncated>
        <difficult>0</difficult>
        <bndbox>
            <xmin>227</xmin>
            <ymin>304</ymin>
            <xmax>639</xmax>
            <ymax>450</ymax>
        </bndbox>
    </object>    <object>
        <name>Abnormal</name>
        <pose>Unspecified</pose>
        <truncated>0</truncated>
        <difficult>0</difficult>
        <bndbox>
            <xmin>452</xmin>
            <ymin>425</ymin>
            <xmax>736</xmax>
            <ymax>538</ymax>
        </bndbox>
    </object>
</annotation>
